serto/__init__.py
serto-0.0.0.dev1.dist-info/AUTHORS
serto-0.0.0.dev1.dist-info/LICENSE
serto-0.0.0.dev1.dist-info/METADATA
serto-0.0.0.dev1.dist-info/WHEEL
serto-0.0.0.dev1.dist-info/entry_points.txt
serto-0.0.0.dev1.dist-info/top_level.txt
serto-0.0.0.dev1.dist-info/RECORD
