Metadata-Version: 2.1
Name: serto
Version: 0.0.0.dev1
Summary: A Python package for optimizing SWMM models for infastructure design, operational control, and emergency response applications
Author: See AUTHORS
Author-email: Caleb Buahin <buahin.caleb@epa.gov>, Anne Mikelonis <mikelonis.anne@epa.gov>
Maintainer-email: Caleb Buahin <buahin.caleb@epa.gov>, Anne Mikelonis <mikelonis.anne@epa.gov>
License: MIT License
Keywords: SWMM,optimization,water,stormwater,modeling
Classifier: Development Status :: 3 - Alpha
Classifier: Intended Audience :: Developers
Classifier: Intended Audience :: Science/Research
Classifier: License :: OSI Approved :: MIT License
Classifier: Programming Language :: Python :: 3
Classifier: Programming Language :: Python :: 3.8
Classifier: Programming Language :: Python :: 3.9
Classifier: Programming Language :: Python :: 3.10
Classifier: Programming Language :: Python :: 3.11
Classifier: Programming Language :: Python :: 3.12
Classifier: Topic :: Scientific/Engineering :: Hydrology
Classifier: Topic :: Scientific/Engineering :: Mathematics
Classifier: Topic :: Scientific/Engineering :: Physics
Classifier: Topic :: Scientific/Engineering :: Artificial Intelligence
Classifier: Topic :: Scientific/Engineering :: GIS
Classifier: Topic :: Scientific/Engineering :: Visualization
Classifier: Topic :: Scientific/Engineering :: Information Analysis
Classifier: Topic :: Software Development :: Libraries
Classifier: Topic :: Software Development :: Libraries :: Python Modules
Classifier: Topic :: Utilities
Requires-Python: >=3.8
License-File: LICENSE
License-File: AUTHORS
Requires-Dist: pandas>=2.2.2
Requires-Dist: pyyaml>=6.0.1
Requires-Dist: pyswmm>=2.0.1
Requires-Dist: mpi4py>=3.1.6
Requires-Dist: shapely>=2.0.5
Requires-Dist: fiona>=1.9.6
Requires-Dist: pyproj>=3.6.1
Requires-Dist: geopandas>=1.0.1
Requires-Dist: matplotlib>=3.9.1
Requires-Dist: plotly>=5.23.0
Requires-Dist: numpy>=1.23.0
Requires-Dist: chama>=0.3.0
Requires-Dist: getmac>=0.9.5
